<annotation>
	<folder>my-project-name</folder>
	<filename>growing_potatoes_2000x.webp</filename>
	<path>/my-project-name/growing_potatoes_2000x.webp</path>
	<source>
		<database>Unspecified</database>
	</source>
	<size>
		<width>1800</width>
		<height>800</height>
		<depth>3</depth>
	</size>
	<object>
		<name>potato</name>
		<pose>Unspecified</pose>
		<truncated>0</truncated>
		<difficult>0</difficult>
		<bndbox>
			<xmin>823</xmin>
			<ymin>469</ymin>
			<xmax>1123</xmax>
			<ymax>742</ymax>
		</bndbox>
	</object>
</annotation>